ollama_api/__init__.py
ollama_api/client.py
ollama_api-0.1.1.dist-info/METADATA
ollama_api-0.1.1.dist-info/WHEEL
ollama_api-0.1.1.dist-info/top_level.txt
ollama_api-0.1.1.dist-info/RECORD
