Metadata-Version: 2.1
Name: ollama-api
Version: 0.1.1
Summary: A Python client for the Ollama API
Home-page: https://github.com/HinxVietti/ollama_api
Author: HinxVietti
Author-email: hinxvietti@gmail.com
Classifier: Programming Language :: Python :: 3
Classifier: License :: OSI Approved :: MIT License
Classifier: Operating System :: OS Independent
Requires-Python: >=3.6
Requires-Dist: requests
